CHANGES.txt
CONTRIBUTORS.txt
LICENSE.txt
MANIFEST.in
README.txt
TODO.txt
setup.py
borinud/__init__.py
borinud/codec.py
borinud/db.py
borinud/ws.py
borinud.egg-info/PKG-INFO
borinud.egg-info/SOURCES.txt
borinud.egg-info/dependency_links.txt
borinud.egg-info/namespace_packages.txt
borinud.egg-info/requires.txt
borinud.egg-info/top_level.txt
borinud/_static/borinud-client.js
borinud/_static/borinud.B.js
borinud/_static/borinud.level.js
borinud/_static/borinud.trange.js
borinud/_static/index.html
doc/source/CHANGES.rst
doc/source/CONTRIBUTORS.rst
doc/source/README.rst
doc/source/TODO.rst
doc/source/api.rst
doc/source/conf.py
doc/source/index.rst