Metadata-Version: 1.0
Name: borinud
Version: 0.7.3
Summary: weather data web api
Home-page: http://www.arpa.emr.it/simc
Author: Emanuele Di Giacomo
Author-email: edigiacomo@arpa.emr.it
License: GPLv2+
Keywords: ARPA SIMC weather station sensor GIS
Platform: UNKNOWN
